runtohills/__init__.py
runtohills/game.py
runtohills/gui.py
runtohills/info.py
runtohills/jar.py
runtohills/jar2.py
runtohills/questions.py
runtohills/sprites.py
runtohills/sql.py
runtohills/sql_mysql.py
runtohills/images/Approach_avatar.png
runtohills/images/Explosion.png
runtohills/images/Falling_avatar.png
runtohills/images/HOME.png
runtohills/images/Mountain1_20.png
runtohills/images/Mountain2_20.png
runtohills/images/Mountain3_20.png
runtohills/images/Mountain4_20.png
runtohills/images/Mountain_0sc.png
runtohills/images/Mountain_10sc.png
runtohills/images/Mountain_5sc.png
runtohills/images/Summit_avatar.png
runtohills/images/__init__.py
runtohills/images/advance.png
runtohills/images/avalanche_avatar.png
runtohills/images/black.png
runtohills/images/blue_ball.png
runtohills/images/blue_ball_small.png
runtohills/images/climbing_avatar.png
runtohills/images/dice1.png
runtohills/images/dice1_big.png
runtohills/images/dice1_green.png
runtohills/images/dice1_red.png
runtohills/images/dice2.png
runtohills/images/dice2_big.png
runtohills/images/dice2_green.png
runtohills/images/dice2_red.png
runtohills/images/dice3.png
runtohills/images/dice3_big.png
runtohills/images/dice3_green.png
runtohills/images/dice3_red.png
runtohills/images/dice4.png
runtohills/images/dice4_big.png
runtohills/images/dice4_green.png
runtohills/images/dice4_red.png
runtohills/images/dice5.png
runtohills/images/dice5_big.png
runtohills/images/dice5_green.png
runtohills/images/dice5_red.png
runtohills/images/dice6.png
runtohills/images/dice6_big.png
runtohills/images/dice6_green.png
runtohills/images/dice6_red.png
runtohills/images/explosion_blue.png
runtohills/images/green.png
runtohills/images/red.png
runtohills/images/red_ball.png
runtohills/images/red_ball_small.png
runtohills/images/white.png
runtohills-1.0.17.dist-info/LICENSE
runtohills-1.0.17.dist-info/METADATA
runtohills-1.0.17.dist-info/WHEEL
runtohills-1.0.17.dist-info/entry_points.txt
runtohills-1.0.17.dist-info/top_level.txt
runtohills-1.0.17.dist-info/RECORD
